ECHO/__init__.py
ECHO/engines/__init__.py
ECHO/engines/shortcuts.py
ECHO/engines/answer_set_planning/__init__.py
ECHO/engines/answer_set_planning/asp_engine.py
ECHO/engines/answer_set_planning/asp_goal_network_encoding.py
ECHO/engines/answer_set_planning/classical_asp_encoding.py
ECHO/engines/echo_planning/__init__.py
ECHO/engines/echo_planning/echo_planning.py
ECHO/engines/mae_epddl_planning/__init__.py
ECHO/engines/mae_epddl_planning/compiler_to_epddl.py
ECHO/engines/mae_epddl_planning/epddl_engine.py
ECHO/engines/mae_epddl_planning/sofai/__init__.py
ECHO/engines/mae_epddl_planning/sofai/architecture_classical.py
ECHO/engines/mae_epddl_planning/sofai/architecture_epistemic.py
ECHO/engines/mae_epddl_planning/sofai/Planners/__init__.py
ECHO/engines/mae_epddl_planning/sofai/Planners/EFP/__init__.py
ECHO/engines/mae_epddl_planning/sofai/Planners/EFP/bin/__init__.py
ECHO/engines/mae_epddl_planning/sofai/Planners/EFP/bin/efp.out
ECHO/engines/mae_epddl_planning/sofai/Planners/EPDDL/__init__.py
ECHO/engines/mae_epddl_planning/sofai/Planners/EPDDL/action.py
ECHO/engines/mae_epddl_planning/sofai/Planners/EPDDL/parser.py
ECHO/engines/mae_epddl_planning/temp/__init__.py
ECHO/model/__init__.py
ECHO/model/action.py
ECHO/model/arithmetic_expression.py
ECHO/model/fluent.py
ECHO/model/ftype.py
ECHO/model/goal.py
ECHO/model/interval.py
ECHO/model/method.py
ECHO/model/predicate.py
ECHO/model/problem.py
ECHO/model/shortcuts.py
ECHO/model/variable.py
echosys-0.1.36.dist-info/LICENSE
echosys-0.1.36.dist-info/METADATA
echosys-0.1.36.dist-info/WHEEL
echosys-0.1.36.dist-info/top_level.txt
echosys-0.1.36.dist-info/RECORD
